SeleniumWise/__init__.py
SeleniumWise/element_interactions.py
SeleniumWise/navigation.py
SeleniumWise/network_tracker.py
SeleniumWise-0.0.1.dist-info/METADATA
SeleniumWise-0.0.1.dist-info/WHEEL
SeleniumWise-0.0.1.dist-info/top_level.txt
SeleniumWise-0.0.1.dist-info/RECORD
