Metadata-Version: 2.1
Name: SeleniumWise
Version: 0.0.1
Summary: Selenium Wrapper
Home-page: https://github.com/zzirakadze/SeleniumWise.git
Author: Zura Zirakadze
Author-email: zirakadzez@gmail.com
License: MIT
Keywords: selenium,python
Classifier: Development Status :: 5 - Production/Stable
Classifier: License :: OSI Approved :: MIT License
Classifier: Programming Language :: Python :: 3.9
Classifier: Operating System :: OS Independent
Requires-Dist: requirements.txt
